{"namespace":"BlueprintDS","components":[{"name":"Badge","sourcePath":"components/general/Badge/Badge.jsx"},{"name":"Button","sourcePath":"components/general/Button/Button.jsx"},{"name":"Dimension","sourcePath":"components/general/Dimension/Dimension.jsx"},{"name":"NumberField","sourcePath":"components/general/NumberField/NumberField.jsx"},{"name":"Panel","sourcePath":"components/general/Panel/Panel.jsx"},{"name":"TitleBlock","sourcePath":"components/general/TitleBlock/TitleBlock.jsx"}],"startingPoints":[],"cards":[{"path":"components/general/Badge/Badge.html","group":"general"},{"path":"components/general/Button/Button.html","group":"general"},{"path":"components/general/Dimension/Dimension.html","group":"general"},{"path":"components/general/NumberField/NumberField.html","group":"general"},{"path":"components/general/Panel/Panel.html","group":"general"},{"path":"components/general/TitleBlock/TitleBlock.html","group":"general"}],"templates":[],"hasThumbnailHtml":false,"globalCssPaths":["fonts/fonts.css","_ds_bundle.css","styles.css"],"tokens":[{"name":"--ds-green","value":"#5ebe83","kind":"color","definedIn":"_ds_bundle.css"},{"name":"--ds-green-bright","value":"#84dba6","kind":"color","definedIn":"_ds_bundle.css"},{"name":"--ds-green-dim","value":"#3e8e5e","kind":"color","definedIn":"_ds_bundle.css"},{"name":"--ds-green-deep","value":"#1c3a2a","kind":"color","definedIn":"_ds_bundle.css"},{"name":"--ds-paper","value":"#0f1518","kind":"color","definedIn":"_ds_bundle.css"},{"name":"--ds-sheet","value":"#121a1e","kind":"color","definedIn":"_ds_bundle.css"},{"name":"--ds-panel","value":"#16201f","kind":"color","definedIn":"_ds_bundle.css"},{"name":"--ds-line","value":"#243036","kind":"color","definedIn":"_ds_bundle.css"},{"name":"--ds-line-2","value":"#2e3c40","kind":"color","definedIn":"_ds_bundle.css"},{"name":"--ds-ink","value":"#dce8e4","kind":"color","definedIn":"_ds_bundle.css"},{"name":"--ds-muted","value":"#7e8c88","kind":"color","definedIn":"_ds_bundle.css"},{"name":"--ds-faint","value":"#54605c","kind":"color","definedIn":"_ds_bundle.css"},{"name":"--ds-dim","value":"#79b9a4","kind":"color","definedIn":"_ds_bundle.css"},{"name":"--ds-display","value":"\"ISOCPEUR\", system-ui, sans-serif","kind":"font","definedIn":"_ds_bundle.css","annotation":"font"},{"name":"--ds-sans","value":"system-ui, -apple-system, \"Segoe UI\", Roboto, sans-serif","kind":"font","definedIn":"_ds_bundle.css","annotation":"font"},{"name":"--ds-mono","value":"ui-monospace, \"SF Mono\", Menlo, Consolas, monospace","kind":"font","definedIn":"_ds_bundle.css","annotation":"font"}],"themes":[],"fonts":[{"family":"ISOCPEUR","weight":"400","style":"normal","cssPath":"fonts/fonts.css","files":["fonts/ISOCPEUR.ttf"]}],"brandFonts":[{"family":"ISOCPEUR","status":"ok","tokens":["--ds-display"],"path":"fonts/fonts.css"}],"source":"design-sync-cli"}